{
    "mask_name": "mask_141374456.npy",
    "mask_height": 1080,
    "mask_width": 1920,
    "promote_type": "mask",
    "labels": {
        "1": {
            "instance_id": 1,
            "class_name": "person",
            "x1": 1494,
            "y1": 123,
            "x2": 1661,
            "y2": 652,
            "logit": 0.0
        },
        "2": {
            "instance_id": 2,
            "class_name": "person",
            "x1": 569,
            "y1": 227,
            "x2": 764,
            "y2": 490,
            "logit": 0.0
        },
        "4": {
            "instance_id": 4,
            "class_name": "person",
            "x1": 569,
            "y1": 228,
            "x2": 734,
            "y2": 435,
            "logit": 0.0
        }
    }
}