{
    "mask_name": "mask_141335256.npy",
    "mask_height": 1080,
    "mask_width": 1920,
    "promote_type": "mask",
    "labels": {
        "1": {
            "instance_id": 1,
            "class_name": "person",
            "x1": 1229,
            "y1": 278,
            "x2": 1548,
            "y2": 1079,
            "logit": 0.0
        },
        "2": {
            "instance_id": 2,
            "class_name": "person",
            "x1": 572,
            "y1": 225,
            "x2": 752,
            "y2": 428,
            "logit": 0.0
        },
        "3": {
            "instance_id": 3,
            "class_name": "person",
            "x1": 572,
            "y1": 224,
            "x2": 755,
            "y2": 576,
            "logit": 0.0
        },
        "4": {
            "instance_id": 4,
            "class_name": "person",
            "x1": 572,
            "y1": 224,
            "x2": 761,
            "y2": 478,
            "logit": 0.0
        }
    }
}